pacab/__init__.py
pacab/actionrunner.py
pacab/audio.py
pacab/constants.py
pacab/dialogrunner.py
pacab/displayinfo.py
pacab/gamesave.py
pacab/gamestate.py
pacab/logger.py
pacab/options.py
pacab/pacab.py
pacab/text.py
pacab/cli/__init__.py
pacab/cli/cli.py
pacab/cli/commands.py
pacab/cli/gamebuilder.py
pacab/menus/__init__.py
pacab/menus/dialogmenu.py
pacab/menus/gamecontrolsmenu.py
pacab/menus/inspectmenu.py
pacab/menus/inventorymenu.py
pacab/menus/loadgamemenu.py
pacab/menus/mainmenu.py
pacab/menus/menutheme.py
pacab/menus/optionsmenu.py
pacab/menus/pausemenu.py
pacab/menus/savemenu.py
pacab/surfaces/__init__.py
pacab/surfaces/animationsurface.py
pacab/surfaces/closebuttonsurface.py
pacab/surfaces/interactionsurface.py
pacab/surfaces/itemsurface.py
pacab/surfaces/navsurface.py
pacab/surfaces/overlaysurface.py
pacab/surfaces/scenesurface.py
pacab/surfaces/transitionsurface.py
pacab/types/__init__.py
pacab/types/action.py
pacab/types/animation.py
pacab/types/animationframes.py
pacab/types/box.py
pacab/types/condition.py
pacab/types/cursorset.py
pacab/types/dialog.py
pacab/types/gamestatevalue.py
pacab/types/inspectaction.py
pacab/types/interaction.py
pacab/types/inventoryitem.py
pacab/types/itemcombination.py
pacab/types/navigation.py
pacab/types/overlay.py
pacab/types/pacabgame.py
pacab/types/prompt.py
pacab/types/reply.py
pacab/types/scene.py
pacab/types/sceneaction.py
pacab/types/sceneitem.py
pacab/types/scenetransition.py
pacab/types/theme.py
pacab-0.1.1.dist-info/licenses/COPYING
pacab-0.1.1.dist-info/METADATA
pacab-0.1.1.dist-info/WHEEL
pacab-0.1.1.dist-info/top_level.txt
pacab-0.1.1.dist-info/RECORD
