Metadata-Version: 2.4
Name: pacab
Version: 0.1.1
Summary: Pacab - The Point and Click Adventure Builder
Home-page: https://gitlab.com/neilsimp1/pacab
Author: neilsimp1
Author-email: Neil Simpson <neilsimp1@gmail.com>
License-Expression: GPL-3.0-only
Project-URL: Homepage, https://gitlab.com/neilsimp1/pacab
Project-URL: Issues, https://gitlab.com/neilsimp1/pacab/-/issues
Project-URL: Source Code, https://gitlab.com/neilsimp1/pacab
Platform: any
Classifier: Programming Language :: Python :: 3
Classifier: Operating System :: OS Independent
Classifier: Topic :: Games/Entertainment
Classifier: Topic :: Software Development :: Libraries :: pygame
Requires-Python: >=3.10
License-File: COPYING
Requires-Dist: pillow
Requires-Dist: pygame-ce
Requires-Dist: pygame-menu-ce
Requires-Dist: pyinstaller
Requires-Dist: toml
Requires-Dist: typer-slim
Dynamic: author
Dynamic: home-page
Dynamic: license-file
Dynamic: platform
Dynamic: requires-python
